{
  "lastUpdated": "18 de mayo de 2026",
  "startDate": "Lunes 18 de mayo de 2026",
  "weeks": [
    {
      "label": "Semana 1",
      "title": "Identidad, fundamentos y criterio comercial",
      "subtitle": "18 ГўВҖВ“ 22 mayo",
      "days": [
        {
          "num": 1,
          "date": "Lunes 18 de mayo",
          "badge": "reunion",
          "sessions": [
            {
              "time": "9:00 a 10:30",
              "owner": "Jorge Pando",
              "slot": "MaГұana",
              "modality": "Presencial",
              "title": "ReuniГіn semanal de equipo вҖ” Bienvenida oficial  ",
              "desc": "PresentaciГіn formal de nuevos agentes В· dinГЎmica del lunes В· cada agente responde en 2 min quiГ©n es, su experiencia comercial y quГ© quiere construir en Inmobiliario Latam",
              "isReunion": true
            },
            {
              "time": "3:00 a 5:00",
              "owner": "Walter Arias",
              "slot": "Tarde",
              "modality": "Virtual",
              "title": "PresentaciГіn e inducciГіn Inmobiliario Latam + Modelo de negocio",
              "desc": "Cultura, valores, estructura de la empresa y roles В· tipos de operaciГіn, comisiones, participaciones y responsabilidades de trazabilidad"
            }
          ]
        },
        {
          "num": 2,
          "date": "Martes 19 de mayo",
          "badge": null,
          "sessions": [
            {
              "time": "9:00 a 11:00",
              "owner": "Jorge Pando",
              "slot": "MaГұana",
              "modality": "Presencial",
              "title": "IntroducciГіn al sector inmobiliario",
              "desc": "Actores del mercado, tipos de inmuebles, proyectos y propiedades usadas В· oportunidades del rubro y diferencias con otros sectores de ventas"
            },
            {
              "time": "3:00 a 5:00",
              "owner": "Jorge Pando",
              "slot": "Tarde",
              "modality": "Presencial",
              "title": "Proceso de compra inmobiliaria y conceptos clave",
              "desc": "Ruta del cliente: reserva, separaciГіn, minuta, escritura, crГ©dito, cuota inicial, partida registral В· glosario mГӯnimo para conversaciones comerciales seguras"
            }
          ]
        },
        {
          "num": 3,
          "date": "MiГғВ©rcoles 20 de mayo",
          "badge": null,
          "sessions": [
            {
              "time": "9:00 a 11:00",
              "owner": "Jorge Pando",
              "slot": "MaГұana",
              "modality": "Presencial",
              "title": "Perfil del comprador inmobiliario",
              "desc": "Motivaciones, miedos y proceso de decisiГіn В· tipos de cliente: inversionista, primera vivienda, familia, crГ©dito, contado e indeciso"
            },
            {
              "time": "3:00 ГўВҖВ“ 5:00",
              "owner": "Jorge Pando",
              "slot": "Tarde",
              "modality": "Presencial",
              "title": "CalificaciГғВіn comercial y matriz del lead",
              "desc": "Presupuesto, zona, forma de pago, urgencia, decisiГғВіn y disponibilidad ГӮВ· plantilla de calificaciГғВіn lista para usar desde el primer lead"
            }
          ]
        },
        {
          "num": 4,
          "date": "Jueves 21 de mayo",
          "badge": null,
          "sessions": [
            {
              "time": "9:00 ГўВҖВ“ 11:00",
              "owner": "Jorge Pando",
              "slot": "MaГұana",
              "modality": "Presencial",
              "title": "Derecho inmobiliario ГўВҖВ” documentaciГғВіn y gestiГғВіn",
              "desc": "Marco legal bГғВЎsico: contratos, escrituras, due diligence ГӮВ· lГғВӯmites del rol del agente ГӮВ· momentos de escalamiento y documentos que debe conocer"
            },
            {
              "time": "3:00 ГўВҖВ“ 5:00",
              "owner": "Camila Bueno / SofГғВӯa HerreГғВұo",
              "slot": "Tarde",
              "modality": "Virtual",
              "title": "OptimizaciГғВіn de perfiles digitales ГўВҖВ” Parte 1: WhatsApp y LinkedIn",
              "desc": "WhatsApp Business y LinkedIn: configuraciГғВіn profesional de perfil, bio, foto y mensaje de bienvenida coherentes con Inmobiliario Latam"
            }
          ]
        },
        {
          "num": 5,
          "date": "Viernes 22 de mayo",
          "badge": null,
          "sessions": [
            {
              "time": "10:00 ГўВҖВ“ 12:00",
              "owner": "Camila Bueno / SofГғВӯa HerreГғВұo",
              "slot": "MaГұana",
              "modality": "Virtual",
              "title": "OptimizaciГғВіn de perfiles digitales ГўВҖВ” Parte 2: Facebook e Instagram",
              "desc": "Facebook e Instagram: configuraciГғВіn profesional de perfil, bio, foto, portada e historias destacadas coherentes con Inmobiliario Latam"
            },
            {
              "time": "2:00 ГўВҖВ“ 3:00",
              "owner": "Camila Bueno / SofГғВӯa HerreГғВұo",
              "slot": "Tarde",
              "modality": "Virtual",
              "title": "Flujo de atenciГғВіn de leads y scripts de primer contacto",
              "desc": "Proceso completo desde la llegada del lead hasta la oportunidad ГӮВ· tipos de leads ГӮВ· criterios de priorizaciГғВіn ГӮВ· mensajes estГғВЎndar para WhatsApp y llamada"
            }
          ]
        }
      ]
    },
    {
      "label": "Semana 2",
      "title": "Herramientas, negociaciГғВіn y habilitaciГғВіn",
      "subtitle": "25 ГўВҖВ“ 29 mayo",
      "days": [
        {
          "num": 6,
          "date": "Lunes 25 de mayo",
          "badge": "reunion",
          "sessions": [
            {
              "time": "9:00 ГўВҖВ“ 10:30",
              "owner": "Jorge Pando",
              "slot": "MaГұana",
              "modality": "Presencial",
              "title": "ReuniГғВіn semanal de equipo",
              "desc": "ParticipaciГғВіn activa ГӮВ· revisiГғВіn de la semana 1 ГӮВ· casos reales del equipo ГӮВ· objetivos de la semana 2",
              "isReunion": true
            },
            {
              "time": "3:00 ГўВҖВ“ 4:30",
              "owner": "SofГғВӯa HerreГғВұo",
              "slot": "Tarde",
              "modality": "Virtual",
              "title": "CRM 1ГӮВӘ cap. ГўВҖВ” PresentaciГғВіn inicial",
              "desc": "IntroducciГғВіn al sistema ГӮВ· mГғВіdulos, flujo base y navegaciГғВіn ГӮВ· contactos, actividades, tareas, estados y primeras cargas guiadas"
            },
            {
              "time": "4:30 ГўВҖВ“ 5:30",
              "owner": "Brooke Villanueva",
              "slot": "Tarde",
              "modality": "Presencial",
              "title": "Notion 1ГӮВӘ cap. ГўВҖВ” Recursos digitales de la empresa",
              "desc": "Bases de datos, guГғВӯas internas, procesos y biblioteca comercial ГӮВ· cГғВіmo navegar y consultar recursos disponibles para el agente"
            }
          ]
        },
        {
          "num": 7,
          "date": "Martes 26 de mayo",
          "badge": null,
          "sessions": [
            {
              "time": "9:00 ГўВҖВ“ 11:00",
              "owner": "Jorge Pando",
              "slot": "MaГұana",
              "modality": "Presencial",
              "title": "TГғВ©cnicas de negociaciГғВіn y manejo de objeciones",
              "desc": "NegociaciГғВіn consultiva y ГғВ©tica ГӮВ· anclas, concesiones, contraofertas ГӮВ· respuestas profesionales ante objeciones frecuentes del rubro inmobiliario"
            },
            {
              "time": "3:00 ГўВҖВ“ 5:00",
              "owner": "Brooke Villanueva",
              "slot": "Tarde",
              "modality": "Presencial",
              "title": "Notion 2ГӮВӘ cap. ГўВҖВ” Inventario y gestiГғВіn de informaciГғВіn",
              "desc": "Carga y consulta de propiedades ГӮВ· lectura de ficha inmobiliaria ГӮВ· estados de disponibilidad ГӮВ· cГғВіmo traducir la ficha en argumentos comerciales"
            }
          ]
        },
        {
          "num": 8,
          "date": "MiГғВ©rcoles 27 de mayo",
          "badge": null,
          "sessions": [
            {
              "time": "10:30 ГўВҖВ“ 12:00",
              "owner": "SofГғВӯa HerreГғВұo",
              "slot": "MaГұana",
              "modality": "Virtual",
              "title": "CRM 2ГӮВӘ cap. ГўВҖВ” GestiГғВіn de leads",
              "desc": "Pipeline y etapas del funnel ГӮВ· actualizaciГғВіn de registros ГӮВ· interacciones, estados, notas y tareas ГӮВ· criterios para avanzar un lead en el sistema"
            },
            {
              "time": "3:00 ГўВҖВ“ 5:00",
              "owner": "Jorge Pando",
              "slot": "Tarde",
              "modality": "Presencial",
              "title": "TГғВ©cnicas de seguimiento y captaciГғВіn de propiedades",
              "desc": "Cadencia comercial sin saturar al cliente ГӮВ· prospecciГғВіn de propietarios ГӮВ· primer contacto ГӮВ· valuaciГғВіn bГғВЎsica y argumentos para captar el inmueble"
            }
          ]
        },
        {
          "num": 9,
          "date": "Jueves 28 de mayo",
          "badge": null,
          "sessions": [
            {
              "time": "10:00 ГўВҖВ“ 12:00",
              "owner": "Jorge Pando",
              "slot": "MaГұana",
              "modality": "Presencial",
              "title": "ACM ГўВҖВ” AnГғВЎlisis comparativo de mercado y presentaciГғВіn comercial",
              "desc": "Criterio para evaluar precio, zona y competencia ГӮВ· cГғВіmo usar el ACM con propietarios y clientes ГӮВ· portales inmobiliarios y publicaciГғВіn efectiva"
            },
            {
              "time": "3:00 ГўВҖВ“ 4:30",
              "owner": "SofГғВӯa HerreГғВұo",
              "slot": "Tarde",
              "modality": "Virtual",
              "title": "CRM 3ГӮВӘ cap. ГўВҖВ” GestiГғВіn de negocios",
              "desc": "CreaciГғВіn y avance de oportunidades en el pipeline ГӮВ· reportes y mГғВ©tricas clave ГӮВ· cierre de negocios en sistema y trazabilidad completa"
            }
          ]
        },
        {
          "num": 10,
          "date": "Viernes 29 de mayo",
          "badge": "eval",
          "sessions": [
            {
              "time": "11:00 ГўВҖВ“ 12:00",
              "owner": "Jorge Pando / SofГғВӯa HerreГғВұo",
              "slot": "MaГұana",
              "modality": "Presencial",
              "title": "SimulaciГғВіn de visita y caso prГғВЎctico en CRM",
              "desc": "Roleplay completo: recepciГғВіn del cliente, recorrido, manejo de objeciones en vivo ГӮВ· caso prГғВЎctico en CRM con trazabilidad completa",
              "isCampo": true
            },
            {
              "time": "3:00 ГўВҖВ“ 5:00",
              "owner": "Walter Arias / Jorge Pando",
              "slot": "Tarde",
              "modality": "Presencial",
              "title": "EvaluaciГғВіn final y plan de acciГғВіn individual",
              "desc": "Test teГғВіrico ГӮВ· roleplay evaluado ГӮВ· feedback individual ГӮВ· plan de mejora ГӮВ· decisiГғВіn de habilitaciГғВіn comercial",
              "isEval": true
            }
          ]
        }
      ]
    }
  ],
  "modules": [
    {
      "num": "0",
      "title": "Pre-onboarding: registro, accesos y diagnГғВіstico",
      "owner": "Camila Bueno",
      "dia": "Previo al DГғВӯa 1"
    },
    {
      "num": "1",
      "title": "ReuniГғВіn de equipo ГўВҖВ” bienvenida y presentaciГғВіn oficial",
      "owner": "Jorge Pando",
      "dia": "DГғВӯa 1 ГӮВ· MaГғВұana 9:00 ГӮВ· Presencial"
    },
    {
      "num": "2",
      "title": "InducciГғВіn Inmobiliario Latam + modelo de negocio",
      "owner": "Walter Arias",
      "dia": "DГғВӯa 1 ГӮВ· Tarde 3:00 ГӮВ· Virtual"
    },
    {
      "num": "3",
      "title": "IntroducciГғВіn al sector inmobiliario",
      "owner": "Jorge Pando",
      "dia": "DГғВӯa 2 ГӮВ· MaГғВұana 9:00 ГӮВ· Presencial"
    },
    {
      "num": "4",
      "title": "Proceso de compra inmobiliaria y conceptos clave",
      "owner": "Jorge Pando",
      "dia": "DГғВӯa 2 ГӮВ· Tarde 3:00 ГӮВ· Presencial"
    },
    {
      "num": "5",
      "title": "Perfil del comprador inmobiliario",
      "owner": "Jorge Pando",
      "dia": "DГғВӯa 3 ГӮВ· MaГғВұana 9:00 ГӮВ· Presencial"
    },
    {
      "num": "6",
      "title": "CalificaciГғВіn comercial y matriz del lead",
      "owner": "Jorge Pando",
      "dia": "DГғВӯa 3 ГӮВ· Tarde 3:00 ГӮВ· Presencial"
    },
    {
      "num": "7",
      "title": "Derecho inmobiliario ГўВҖВ” documentaciГғВіn y gestiГғВіn",
      "owner": "Jorge Pando",
      "dia": "DГғВӯa 4 ГӮВ· MaГғВұana 9:00 ГӮВ· Presencial"
    },
    {
      "num": "8",
      "title": "OptimizaciГғВіn perfiles ГўВҖВ” Parte 1: WhatsApp y LinkedIn",
      "owner": "Camila Bueno / SofГғВӯa HerreГғВұo",
      "dia": "DГғВӯa 4 ГӮВ· Tarde 3:00 ГӮВ· Virtual"
    },
    {
      "num": "9",
      "title": "OptimizaciГғВіn perfiles ГўВҖВ” Parte 2: Facebook e Instagram",
      "owner": "Camila Bueno / SofГғВӯa HerreГғВұo",
      "dia": "DГғВӯa 5 ГӮВ· MaГғВұana 10:00 ГӮВ· Virtual"
    },
    {
      "num": "10",
      "title": "Flujo de atenciГғВіn de leads y scripts de primer contacto",
      "owner": "Camila Bueno / SofГғВӯa HerreГғВұo",
      "dia": "DГғВӯa 5 ГӮВ· Tarde 2:00 ГӮВ· Virtual"
    },
    {
      "num": "11",
      "title": "ReuniГғВіn de equipo ГўВҖВ” semana 2",
      "owner": "Jorge Pando",
      "dia": "DГғВӯa 6 ГӮВ· MaГғВұana 9:00 ГӮВ· Presencial"
    },
    {
      "num": "12",
      "title": "CRM 1ГӮВӘ cap. ГўВҖВ” PresentaciГғВіn inicial",
      "owner": "SofГғВӯa HerreГғВұo",
      "dia": "DГғВӯa 6 ГӮВ· Tarde 3:00 ГӮВ· Virtual"
    },
    {
      "num": "13",
      "title": "Notion 1ГӮВӘ cap. ГўВҖВ” Recursos digitales de la empresa",
      "owner": "Brooke Villanueva",
      "dia": "DГғВӯa 6 ГӮВ· Tarde 4:30 ГӮВ· Presencial"
    },
    {
      "num": "14",
      "title": "TГғВ©cnicas de negociaciГғВіn y manejo de objeciones",
      "owner": "Jorge Pando",
      "dia": "DГғВӯa 7 ГӮВ· MaГғВұana 9:00 ГӮВ· Presencial"
    },
    {
      "num": "15",
      "title": "Notion 2ГӮВӘ cap. ГўВҖВ” Inventario y gestiГғВіn de informaciГғВіn",
      "owner": "Brooke Villanueva",
      "dia": "DГғВӯa 7 ГӮВ· Tarde 3:00 ГӮВ· Presencial"
    },
    {
      "num": "16",
      "title": "CRM 2ГӮВӘ cap. ГўВҖВ” GestiГғВіn de leads",
      "owner": "SofГғВӯa HerreГғВұo",
      "dia": "DГғВӯa 8 ГӮВ· MaГғВұana 10:30 ГӮВ· Virtual"
    },
    {
      "num": "17",
      "title": "TГғВ©cnicas de seguimiento y captaciГғВіn de propiedades",
      "owner": "Jorge Pando",
      "dia": "DГғВӯa 8 ГӮВ· Tarde 3:00 ГӮВ· Presencial"
    },
    {
      "num": "18",
      "title": "ACM + presentaciГғВіn comercial de propiedades y portales",
      "owner": "Jorge Pando",
      "dia": "DГғВӯa 9 ГӮВ· MaГғВұana 10:00 ГӮВ· Presencial"
    },
    {
      "num": "19",
      "title": "CRM 3ГӮВӘ cap. ГўВҖВ” GestiГғВіn de negocios",
      "owner": "SofГғВӯa HerreГғВұo",
      "dia": "DГғВӯa 9 ГӮВ· Tarde 3:00 ГӮВ· Virtual"
    },
    {
      "num": "20",
      "title": "SimulaciГғВіn de visita y caso prГғВЎctico en CRM",
      "owner": "Jorge Pando / SofГғВӯa HerreГғВұo",
      "dia": "DГғВӯa 10 ГӮВ· MaГғВұana 11:00 ГӮВ· Presencial"
    },
    {
      "num": "21",
      "title": "EvaluaciГғВіn final y plan de acciГғВіn individual",
      "owner": "Walter Arias / Jorge Pando",
      "dia": "DГғВӯa 10 ГӮВ· Tarde 3:00 ГӮВ· Presencial"
    },
    {
      "num": "22",
      "title": "AcompaГғВұamiento supervisado ГўВҖВ” 30 dГғВӯas post-habilitaciГғВіn",
      "owner": "LГғВӯder comercial",
      "dia": "Post DГғВӯa 10"
    }
  ]
}